fork_github_repo/__init__.py
fork_github_repo-1.2.0.dist-info/METADATA
fork_github_repo-1.2.0.dist-info/WHEEL
fork_github_repo-1.2.0.dist-info/entry_points.txt
fork_github_repo-1.2.0.dist-info/top_level.txt
fork_github_repo-1.2.0.dist-info/RECORD
