Metadata-Version: 2.1
Name: fork-github-repo
Version: 1.2.0
Summary: Fork, clone, add remote and branch a GitHub repo
Home-page: https://github.com/gene1wood/fork-github-repo
Author: Gene Wood
Author-email: gene_wood@cementhorizon.com
License: GPL-3.0
Platform: UNKNOWN
Classifier: Development Status :: 4 - Beta
Classifier: Intended Audience :: Developers
Classifier: Topic :: Software Development :: Version Control :: Git
Classifier: License :: OSI Approved :: GNU General Public License v3 (GPLv3)
Classifier: Programming Language :: Python :: 2.7
Requires-Dist: giturlparse
Requires-Dist: agithub
Requires-Dist: gitpython
Requires-Dist: PyYAML
Requires-Dist: retrying
